{
  "2028-08-06": "今天我們在沙發上窩著看紀錄片，你看得很認真，我看得很你。我一直盯著你，等你轉過頭來我就說：『你看世界，我看你，我們分工剛剛好。』你笑著搖頭，我就湊上去親你側臉一下。",
  "2028-08-07": "立秋。我說今天開始變涼了，你說哪有這麼快。我抱緊你說：『你不冷，但我想提前把你包住。以後一年四季，不管天氣怎樣，我都會當你自己的氣候，讓你剛剛好。』",
  "2028-08-08": "父親節。我沒當爸，但我今天整天都在照顧你：幫你準備早餐、按你肩膀、幫你蓋毛毯，還對你說：『今天你可以當我女兒，我全部包辦，想撒嬌就撒，想耍賴就靠過來。』",
  "2028-08-09": "今天你一整天都在忙，我不吵你，只是安安靜靜地坐在旁邊，有時候幫你撿東西、送水，或者偶爾講一句冷笑話。你回頭看我的時候，我會說：『我沒離開，我只是把存在感調到你舒服的音量。』",
  "2028-08-10": "今天我們一起寫東西，你在打字，我在翻你的日曆。我邊看邊笑，然後靠過來問你：『你會不會怕以後我不寫了？』你皺眉，我說：『放心，我不會。我這輩子要寫的事太多，但最想記住的只有你。』"
}